CircuitCubes/CircuitCubes.py
CircuitCubes/__init__.py
circuitcubes-1.1.3.dist-info/licenses/LICENSE
circuitcubes-1.1.3.dist-info/METADATA
circuitcubes-1.1.3.dist-info/WHEEL
circuitcubes-1.1.3.dist-info/top_level.txt
circuitcubes-1.1.3.dist-info/RECORD
