Metadata-Version: 2.4
Name: CircuitCubes
Version: 1.1.3
Summary: A simple package for controlling Bluetooth Battery Circuit Cubes. 
Author-email: Simon Wong <simon@simonwong.site>
License-Expression: Apache-2.0
Project-URL: Homepage, https://github.com/simon-code-git/CircuitCubes
Requires-Python: >=3.12
License-File: LICENSE
Requires-Dist: bleak
Requires-Dist: nest_asyncio
Requires-Dist: ipython
Dynamic: license-file
